logupdate/__init__.py
logupdate/core.py
logupdate-0.3.1.dist-info/LICENSE
logupdate-0.3.1.dist-info/WHEEL
logupdate-0.3.1.dist-info/METADATA
logupdate-0.3.1.dist-info/RECORD
