Metadata-Version: 2.1
Name: logupdate
Version: 0.3.1
Summary: Log by overwriting the previous output in the terminal
Home-page: https://github.com/CoorpAcademy/pino.py
License: MIT
Keywords: cli,terminal,log,logger,logging,shell,update,animation,progress
Author: Adriean Khisbe
Author-email: adriean.khisbe@live.fr
Requires-Python: >=3.6,<4.0
Classifier: Development Status :: 4 - Beta
Classifier: Environment :: Console
Classifier: Intended Audience :: Developers
Classifier: License :: OSI Approved :: MIT License
Classifier: Operating System :: OS Independent
Classifier: Programming Language :: Python
Classifier: Programming Language :: Python :: 3
Classifier: Programming Language :: Python :: 3.5
Classifier: Programming Language :: Python :: 3.6
Classifier: Programming Language :: Python :: 3.7
Classifier: Programming Language :: Python :: 3.8
Classifier: Programming Language :: Python :: Implementation :: PyPy
Classifier: Topic :: Software Development :: Libraries :: Python Modules
Classifier: Topic :: System :: Logging
Requires-Dist: ansiwrap (>=0.8.4,<0.9.0)
Requires-Dist: cursor (>=1.3.4,<2.0.0)
